glsurface/__init__.py
glsurface/glsurface.py
glsurface/version.py
glsurface-0.1.2.dist-info/LICENSE
glsurface-0.1.2.dist-info/METADATA
glsurface-0.1.2.dist-info/WHEEL
glsurface-0.1.2.dist-info/top_level.txt
glsurface-0.1.2.dist-info/RECORD
