Metadata-Version: 2.2
Name: glsurface
Version: 0.1.2
Summary: Some helper class
Author-email: Tianzhu Qiao <tq@feiyilin.com>
License: MIT License
Project-URL: Homepage, https://github.com/tianzhuqiao/glsurface
Classifier: Operating System :: OS Independent
Requires-Python: >=3.0
License-File: LICENSE
Requires-Dist: wxpython>=4.2.1
Requires-Dist: PyOpenGL>=3.1.9
Requires-Dist: PyOpenGL-accelerate>=3.1.9
